zen_garden_timer/__init__.py
zen_garden_timer/background_music.mp3
zen_garden_timer-0.1.4.dist-info/licenses/LICENSE
zen_garden_timer-0.1.4.dist-info/METADATA
zen_garden_timer-0.1.4.dist-info/WHEEL
zen_garden_timer-0.1.4.dist-info/entry_points.txt
zen_garden_timer-0.1.4.dist-info/top_level.txt
zen_garden_timer-0.1.4.dist-info/RECORD
