Metadata-Version: 2.4
Name: zen-garden-timer
Version: 0.1.4
Summary: A beautiful CLI productivity timer with growing plants and an adorable snail
Author-email: Aidan McConnon <aidanmcconnon210@gmail.com>
License: MIT
Project-URL: Homepage, https://github.com/PndaMan/zen-garden-cli
Project-URL: Repository, https://github.com/PndaMan/zen-garden-cli
Keywords: productivity,timer,pomodoro,zen,cli
Classifier: Development Status :: 4 - Beta
Classifier: Intended Audience :: End Users/Desktop
Classifier: License :: OSI Approved :: MIT License
Classifier: Programming Language :: Python :: 3
Classifier: Programming Language :: Python :: 3.8
Classifier: Programming Language :: Python :: 3.9
Classifier: Programming Language :: Python :: 3.10
Classifier: Programming Language :: Python :: 3.11
Classifier: Programming Language :: Python :: 3.12
Requires-Python: >=3.8
License-File: LICENSE
Requires-Dist: readchar>=4.0.0
Requires-Dist: pygame>=2.5.0
Requires-Dist: rich>=13.0.0
Requires-Dist: plyer>=2.1.0
Dynamic: license-file
